// Code generated by "stringer -type=Op -linecomment=true"; DO NOT EDIT.

package bytecode

import "strconv"

func _() {
	// An "invalid array index" compiler error signifies that the constant values have changed.
	// Re-run the stringer command to generate them again.
	var x [1]struct{}
	_ = x[Nop-0]
	_ = x[Aconstnull-1]
	_ = x[Iconstm1-2]
	_ = x[Iconst0-3]
	_ = x[Iconst1-4]
	_ = x[Iconst2-5]
	_ = x[Iconst3-6]
	_ = x[Iconst4-7]
	_ = x[Iconst5-8]
	_ = x[Lconst0-9]
	_ = x[Lconst1-10]
	_ = x[Fconst0-11]
	_ = x[Fconst1-12]
	_ = x[Fconst2-13]
	_ = x[Dconst0-14]
	_ = x[Dconst1-15]
	_ = x[Bipush-16]
	_ = x[Sipush-17]
	_ = x[Ldc-18]
	_ = x[Ldcw-19]
	_ = x[Ldc2w-20]
	_ = x[Iload-21]
	_ = x[Lload-22]
	_ = x[Fload-23]
	_ = x[Dload-24]
	_ = x[Aload-25]
	_ = x[Iload0-26]
	_ = x[Iload1-27]
	_ = x[Iload2-28]
	_ = x[Iload3-29]
	_ = x[Lload0-30]
	_ = x[Lload1-31]
	_ = x[Lload2-32]
	_ = x[Lload3-33]
	_ = x[Fload0-34]
	_ = x[Fload1-35]
	_ = x[Fload2-36]
	_ = x[Fload3-37]
	_ = x[Dload0-38]
	_ = x[Dload1-39]
	_ = x[Dload2-40]
	_ = x[Dload3-41]
	_ = x[Aload0-42]
	_ = x[Aload1-43]
	_ = x[Aload2-44]
	_ = x[Aload3-45]
	_ = x[Iaload-46]
	_ = x[Laload-47]
	_ = x[Faload-48]
	_ = x[Daload-49]
	_ = x[Aaload-50]
	_ = x[Baload-51]
	_ = x[Caload-52]
	_ = x[Saload-53]
	_ = x[Istore-54]
	_ = x[Lstore-55]
	_ = x[Fstore-56]
	_ = x[Dstore-57]
	_ = x[Astore-58]
	_ = x[Istore0-59]
	_ = x[Istore1-60]
	_ = x[Istore2-61]
	_ = x[Istore3-62]
	_ = x[Lstore0-63]
	_ = x[Lstore1-64]
	_ = x[Lstore2-65]
	_ = x[Lstore3-66]
	_ = x[Fstore0-67]
	_ = x[Fstore1-68]
	_ = x[Fstore2-69]
	_ = x[Fstore3-70]
	_ = x[Dstore0-71]
	_ = x[Dstore1-72]
	_ = x[Dstore2-73]
	_ = x[Dstore3-74]
	_ = x[Astore0-75]
	_ = x[Astore1-76]
	_ = x[Astore2-77]
	_ = x[Astore3-78]
	_ = x[Iastore-79]
	_ = x[Lastore-80]
	_ = x[Fastore-81]
	_ = x[Dastore-82]
	_ = x[Aastore-83]
	_ = x[Bastore-84]
	_ = x[Castore-85]
	_ = x[Sastore-86]
	_ = x[Pop-87]
	_ = x[Pop2-88]
	_ = x[Dup-89]
	_ = x[Dupx1-90]
	_ = x[Dupx2-91]
	_ = x[Dup2-92]
	_ = x[Dup2x1-93]
	_ = x[Dup2x2-94]
	_ = x[Swap-95]
	_ = x[Iadd-96]
	_ = x[Ladd-97]
	_ = x[Fadd-98]
	_ = x[Dadd-99]
	_ = x[Isub-100]
	_ = x[Lsub-101]
	_ = x[Fsub-102]
	_ = x[Dsub-103]
	_ = x[Imul-104]
	_ = x[Lmul-105]
	_ = x[Fmul-106]
	_ = x[Dmul-107]
	_ = x[Idiv-108]
	_ = x[Ldiv-109]
	_ = x[Fdiv-110]
	_ = x[Ddiv-111]
	_ = x[Irem-112]
	_ = x[Lrem-113]
	_ = x[Frem-114]
	_ = x[Drem-115]
	_ = x[Ineg-116]
	_ = x[Lneg-117]
	_ = x[Fneg-118]
	_ = x[Dneg-119]
	_ = x[Ishl-120]
	_ = x[Lshl-121]
	_ = x[Ishr-122]
	_ = x[Lshr-123]
	_ = x[Iushr-124]
	_ = x[Lushr-125]
	_ = x[Iand-126]
	_ = x[Land-127]
	_ = x[Ior-128]
	_ = x[Lor-129]
	_ = x[Ixor-130]
	_ = x[Lxor-131]
	_ = x[Iinc-132]
	_ = x[I2l-133]
	_ = x[I2f-134]
	_ = x[I2d-135]
	_ = x[L2i-136]
	_ = x[L2f-137]
	_ = x[L2d-138]
	_ = x[F2i-139]
	_ = x[F2l-140]
	_ = x[F2d-141]
	_ = x[D2i-142]
	_ = x[D2l-143]
	_ = x[D2f-144]
	_ = x[I2b-145]
	_ = x[I2c-146]
	_ = x[I2s-147]
	_ = x[Lcmp-148]
	_ = x[Fcmpl-149]
	_ = x[Fcmpg-150]
	_ = x[Dcmpl-151]
	_ = x[Dcmpg-152]
	_ = x[Ifeq-153]
	_ = x[Ifne-154]
	_ = x[Iflt-155]
	_ = x[Ifge-156]
	_ = x[Ifgt-157]
	_ = x[Ifle-158]
	_ = x[Ificmpeq-159]
	_ = x[Ificmpne-160]
	_ = x[Ificmplt-161]
	_ = x[Ificmpge-162]
	_ = x[Ificmpgt-163]
	_ = x[Ificmple-164]
	_ = x[Ifacmpeq-165]
	_ = x[Ifacmpne-166]
	_ = x[Goto-167]
	_ = x[Jsr-168]
	_ = x[Ret-169]
	_ = x[Ireturn-172]
	_ = x[Lreturn-173]
	_ = x[Freturn-174]
	_ = x[Dreturn-175]
	_ = x[Areturn-176]
	_ = x[Return-177]
	_ = x[Getstatic-178]
	_ = x[Putstatic-179]
	_ = x[Getfield-180]
	_ = x[Putfield-181]
	_ = x[Invokevirtual-182]
	_ = x[Invokespecial-183]
	_ = x[Invokestatic-184]
	_ = x[Invokeinterface-185]
	_ = x[Invokedynamic-186]
	_ = x[New-187]
	_ = x[Newarray-188]
	_ = x[Anewarray-189]
	_ = x[Arraylength-190]
	_ = x[Athrow-191]
	_ = x[Checkcast-192]
	_ = x[Instanceof-193]
	_ = x[Monitorenter-194]
	_ = x[Monitorexit-195]
	_ = x[Multianewarray-197]
	_ = x[Ifnull-198]
	_ = x[Ifnonnull-199]
	_ = x[Gotow-200]
	_ = x[Jsrw-201]
	_ = x[Breakpoint-202]
	_ = x[Impdep1-254]
	_ = x[Impdep2-255]
}

const (
	_Op_name_0 = "nopaconst_nulliconst_m1iconst_0iconst_1iconst_2iconst_3iconst_4iconst_5lconst_0lconst_1fconst_0fconst_1fconst_2dconst_0dconst_1bipushsipushldcldc_wldc2_wiloadlloadfloaddloadaloadiload_0iload_1iload_2iload_3lload_0lload_1lload_2lload_3fload_0fload_1fload_2fload_3dload_0dload_1dload_2dload_3aload_0aload_1aload_2aload_3ialoadlaloadfaloaddaloadaaloadbaloadcaloadsaloadistorelstorefstoredstoreastoreistore_0istore_1istore_2istore_3lstore_0lstore_1lstore_2lstore_3fstore_0fstore_1fstore_2fstore_3dstore_0dstore_1dstore_2dstore_3astore_0astore_1astore_2astore_3iastorelastorefastoredastoreaastorebastorecastoresastorepoppop2dupdup_x1dup_x2dup2dup2_x1dup2_x2swapiaddladdfadddaddisublsubfsubdsubimullmulfmuldmulidivldivfdivddiviremlremfremdremineglnegfnegdnegishllshlishrlshriushrlushriandlandiorlorixorlxoriinci2li2fi2dl2il2fl2df2if2lf2dd2id2ld2fi2bi2ci2slcmpfcmplfcmpgdcmpldcmpgifeqifneifltifgeifgtifleif_icmpeqif_icmpneif_icmpltif_icmpgeif_icmpgtif_icmpleif_acmpeqif_acmpnegotojsrret"
	_Op_name_1 = "ireturnlreturnfreturndreturnareturnreturngetstaticputstaticgetfieldputfieldinvokevirtualinvokespecialinvokestaticinvokeinterfaceinvokedynamicnewnewarrayanewarrayarraylengthathrowcheckcastinstanceofmonitorentermonitorexit"
	_Op_name_2 = "multianewarrayifnullifnonnullgoto_wjsr_wbreakpoint"
	_Op_name_3 = "impdep1impdep2"
)

var (
	_Op_index_0 = [...]uint16{0, 3, 14, 23, 31, 39, 47, 55, 63, 71, 79, 87, 95, 103, 111, 119, 127, 133, 139, 142, 147, 153, 158, 163, 168, 173, 178, 185, 192, 199, 206, 213, 220, 227, 234, 241, 248, 255, 262, 269, 276, 283, 290, 297, 304, 311, 318, 324, 330, 336, 342, 348, 354, 360, 366, 372, 378, 384, 390, 396, 404, 412, 420, 428, 436, 444, 452, 460, 468, 476, 484, 492, 500, 508, 516, 524, 532, 540, 548, 556, 563, 570, 577, 584, 591, 598, 605, 612, 615, 619, 622, 628, 634, 638, 645, 652, 656, 660, 664, 668, 672, 676, 680, 684, 688, 692, 696, 700, 704, 708, 712, 716, 720, 724, 728, 732, 736, 740, 744, 748, 752, 756, 760, 764, 768, 773, 778, 782, 786, 789, 792, 796, 800, 804, 807, 810, 813, 816, 819, 822, 825, 828, 831, 834, 837, 840, 843, 846, 849, 853, 858, 863, 868, 873, 877, 881, 885, 889, 893, 897, 906, 915, 924, 933, 942, 951, 960, 969, 973, 976, 979}
	_Op_index_1 = [...]uint8{0, 7, 14, 21, 28, 35, 41, 50, 59, 67, 75, 88, 101, 113, 128, 141, 144, 152, 161, 172, 178, 187, 197, 209, 220}
	_Op_index_2 = [...]uint8{0, 14, 20, 29, 35, 40, 50}
	_Op_index_3 = [...]uint8{0, 7, 14}
)

func (i Op) String() string {
	switch {
	case i <= 169:
		return _Op_name_0[_Op_index_0[i]:_Op_index_0[i+1]]
	case 172 <= i && i <= 195:
		i -= 172
		return _Op_name_1[_Op_index_1[i]:_Op_index_1[i+1]]
	case 197 <= i && i <= 202:
		i -= 197
		return _Op_name_2[_Op_index_2[i]:_Op_index_2[i+1]]
	case 254 <= i && i <= 255:
		i -= 254
		return _Op_name_3[_Op_index_3[i]:_Op_index_3[i+1]]
	default:
		return "Op(" + strconv.FormatInt(int64(i), 10) + ")"
	}
}
